{
    "_settings": {
        "defaultAlbedo": "gamedata/textures/materials/blocks/albedo/neutral.png",
        "defaultEmissive": "gamedata/textures/materials/blocks/emissiveMaskAlpha/neutral.png",
        "defaultHeight": "gamedata/textures/materials/blocks/heightSmoothnessSpecularity/neutral.png",
        "defaultNormal": "gamedata/textures/materials/blocks/normal/neutral.png",
        "fileExtension": ".png",
        "folderAlbedo": "./../../Textures/albedo/Growables/",
        "folderEmissive": "./../../Textures/emissive/Growables/",
        "folderHeight": "./../../Textures/height/Growables/",
        "folderNormal": "./../../Textures/normal/Growables/"
    },
	"Ulfric.ColonyAddOns.Blocks.LeavesApples" : {
		"albedo" : "LeavesApples"
	},
	"Ulfric.ColonyAddOns.Blocks.AppleBarrel": {
     "albedo": "AppleBarrel"
    },
	"Ulfric.ColonyAddOns.Blocks.AppleBasket" : {
		 "albedo" : "AppleBasket"
	},
	"Ulfric.ColonyAddOns.Blocks.BasketTop" : {
		 "albedo" : "BasketTop"
	},
	"Ulfric.ColonyAddOns.Blocks.Basket" : {
		 "albedo" : "Basket"
	},
	"Ulfric.ColonyAddOns.Blocks.CherryBasket" : {
		 "albedo" : "CherryBasket"
	}
}